Workbook
Name aporte: [1]APP!$D$17
Name aporte_mensal: Simulador!$E$17
Name cinco_anos: Simulador!$A$23
Name dez_anos: Simulador!$A$24
Name dois_anos: Simulador!$A$22
Name investimento_mensal: Simulador!$E$11
Name patrimonio: [1]APP!$D$20
Name patrimonio_acumulado: Simulador!$E$18
Name percentual_investimento: Simulador!$E$10
Name qtd_anos: [1]APP!$D$18
Name rendimento_carteira: [1]APP!$D$13
Name rendimento_carteira: Simulador!$E$9
Name salario_mensal: Simulador!$E$8
Name taxa_fundo: Simulador!$E$16
Name taxa_mensal: [1]APP!$D$19
Name tempo_investimento: Simulador!$E$15
Name trinta_anos: Simulador!$A$26
Name vinte_anos: Simulador!$A$25

Sheet Simulador
C1: SIMULADOR DE INVESTIMENTOS
B7: PARÂMETROS | G7: DISTRIBUIÇÃO POR PERFIL
B8: Salário Mensal (R$) | E8: 4000 | G8: PERFIL | I8: Moderado
B9: Rendimento Carteira (%) | E9: 0.006 | G9: INVESTIMENTO MENSAL | I9: =investimento_mensal -> 400
B10: Percentual de Investimento (%) | E10: 0.1
B11: Investimento Mensal (R$) | E11: =E8*E10 -> 400 | G11: TIPO DE FII | H11: PERCENTUAL SUGERIDO | I11: VALORES
G12: PAPEL | H12: =VLOOKUP($I$8&"-"&G12,Auxiliar!A:D,4,FALSE) -> 0.32 | I12: =$I$9*H12 -> 128
B13: INVESTIMENTO | G13: TIJOLO | H13: =VLOOKUP($I$8&"-"&G13,Auxiliar!A:D,4,FALSE) -> 0.35 | I13: =$I$9*H13 -> 140
G14: HÍBRIDOS | H14: =VLOOKUP($I$8&"-"&G14,Auxiliar!A:D,4,FALSE) -> 0.08 | I14: =$I$9*H14 -> 32
B15: Tempo (Anos) | E15: 10 | G15: FOFs | H15: =VLOOKUP($I$8&"-"&G15,Auxiliar!A:D,4,FALSE) -> 0.05 | I15: =$I$9*H15 -> 20
B16: Taxa de Rendimento Mensal (%) | E16: 0.01079 | G16: DESENVOLVIMENTO | H16: =VLOOKUP($I$8&"-"&G16,Auxiliar!A:D,4,FALSE) -> 0.1 | I16: =$I$9*H16 -> 40
B17: Investimento Mensal (R$) | E17: =investimento_mensal -> 400 | G17: HOTELARIAS | H17: =VLOOKUP($I$8&"-"&G17,Auxiliar!A:D,4,FALSE) -> 0.1 | I17: =$I$9*H17 -> 40
B18: Patrimônio Acumulado (R$) | E18: =FV(taxa_fundo,(tempo_investimento*12),(aporte_mensal*-1)) -> 97313.685 | G18: TOTAL | H18: =SUM(H12:H17) -> 1 | I18: =SUM(I12:I17) -> 400
B19: Dividendos Mensais (R$) | E19: =patrimonio_acumulado*rendimento_carteira -> 583.88211
B21: CENÁRIOS | D21: Patrimônio | E21: Dividendos
A22: 2 | B22: 2 Anos | D22: =FV(taxa_fundo,(dois_anos*12),(aporte_mensal*-1)) -> 10891.051 | E22: =D22*rendimento_carteira -> 65.346306
A23: 5 | B23: 5 Anos | D23: =FV(taxa_fundo,(cinco_anos*12),(aporte_mensal*-1)) -> 33510.766 | E23: =D23*rendimento_carteira -> 201.06459
A24: 10 | B24: 10 Anos | D24: =FV(taxa_fundo,(dez_anos*12),(aporte_mensal*-1)) -> 97313.685 | E24: =D24*rendimento_carteira -> 583.88211
A25: 20 | B25: 20 Anos | D25: =FV(taxa_fundo,(vinte_anos*12),(aporte_mensal*-1)) -> 450079.36 | E25: =D25*rendimento_carteira -> 2700.4762
A26: 30 | B26: 30 Anos | D26: =FV(taxa_fundo,(trinta_anos*12),(aporte_mensal*-1)) -> 1728867.9 | E26: =D26*rendimento_carteira -> 10373.207

Sheet Auxiliar
A2: CHAVE | B2: PERFIL | C2: TIPO DE FII | D2: %
A3: =B3&"-"&C3 -> Conservador-PAPEL | B3: Conservador | C3: PAPEL | D3: 0.3 | H3: %
A4: =B4&"-"&C4 -> Conservador-TIJOLO | B4: Conservador | C4: TIJOLO | D4: 0.5 | G4: Moderado-TIJOLO | H4: =VLOOKUP(G4,$A:$D,4,FALSE) -> 0.35
A5: =B5&"-"&C5 -> Conservador-HÍBRIDOS | B5: Conservador | C5: HÍBRIDOS | D5: 0.1
A6: =B6&"-"&C6 -> Conservador-FOFs | B6: Conservador | C6: FOFs | D6: 0.1
A7: =B7&"-"&C7 -> Conservador-DESENVOLVIMENTO | B7: Conservador | C7: DESENVOLVIMENTO | D7: 0
A8: =B8&"-"&C8 -> Conservador-HOTELARIAS | B8: Conservador | C8: HOTELARIAS | D8: 0
A9: =B9&"-"&C9 -> Moderado-PAPEL | B9: Moderado | C9: PAPEL | D9: 0.32
A10: =B10&"-"&C10 -> Moderado-TIJOLO | B10: Moderado | C10: TIJOLO | D10: 0.35
A11: =B11&"-"&C11 -> Moderado-HÍBRIDOS | B11: Moderado | C11: HÍBRIDOS | D11: 0.08
A12: =B12&"-"&C12 -> Moderado-FOFs | B12: Moderado | C12: FOFs | D12: 0.05
A13: =B13&"-"&C13 -> Moderado-DESENVOLVIMENTO | B13: Moderado | C13: DESENVOLVIMENTO | D13: 0.1
A14: =B14&"-"&C14 -> Moderado-HOTELARIAS | B14: Moderado | C14: HOTELARIAS | D14: 0.1
A15: =B15&"-"&C15 -> Agressivo-PAPEL | B15: Agressivo | C15: PAPEL | D15: 0.5
A16: =B16&"-"&C16 -> Agressivo-TIJOLO | B16: Agressivo | C16: TIJOLO | D16: 0.1
... A20: =B20&"-"&C20 -> Agressivo-HOTELARIAS | B20: Agressivo | C20: HOTELARIAS | D20: 0.1
